posteriors/__init__.py
posteriors/optim.py
posteriors/torchopt.py
posteriors/tree_utils.py
posteriors/types.py
posteriors/utils.py
posteriors/ekf/__init__.py
posteriors/ekf/dense_fisher.py
posteriors/ekf/diag_fisher.py
posteriors/laplace/__init__.py
posteriors/laplace/dense_fisher.py
posteriors/laplace/dense_ggn.py
posteriors/laplace/dense_hessian.py
posteriors/laplace/diag_fisher.py
posteriors/laplace/diag_ggn.py
posteriors/sgmcmc/__init__.py
posteriors/sgmcmc/baoa.py
posteriors/sgmcmc/sghmc.py
posteriors/sgmcmc/sgld.py
posteriors/sgmcmc/sgnht.py
posteriors/vi/__init__.py
posteriors/vi/dense.py
posteriors/vi/diag.py
posteriors-0.1.2.dist-info/licenses/LICENSE
posteriors-0.1.2.dist-info/METADATA
posteriors-0.1.2.dist-info/WHEEL
posteriors-0.1.2.dist-info/top_level.txt
posteriors-0.1.2.dist-info/RECORD
