Metadata-Version: 2.4
Name: posteriors
Version: 0.1.2
Summary: Uncertainty quantification with PyTorch
Author-email: Sam Duffield <sam@normalcomputing.ai>
License: Apache-2.0
Keywords: pytorch,uncertainty
Classifier: Programming Language :: Python :: 3
Classifier: Topic :: Scientific/Engineering :: Mathematics
Classifier: License :: OSI Approved :: Apache Software License
Requires-Python: >=3.9
License-File: LICENSE
Requires-Dist: torch>=2.0.0
Requires-Dist: torchopt>=0.7.3
Requires-Dist: optree>=0.17.0
Requires-Dist: tensordict>=0.7.0
Provides-Extra: test
Requires-Dist: pre-commit; extra == "test"
Requires-Dist: pytest-cov; extra == "test"
Requires-Dist: pytest-xdist; extra == "test"
Requires-Dist: ruff; extra == "test"
Provides-Extra: docs
Requires-Dist: mkdocs; extra == "docs"
Requires-Dist: mkdocs-material; extra == "docs"
Requires-Dist: mkdocstrings[python]; extra == "docs"
Dynamic: license-file
